{"model":"taki_other_202504.moc","physics":"taki_other_202504.physics.json","textures":["texture_00.png","texture_01.png"],"transition":{"bundleName":"live2d/chara/040_general","fileName":"takiTransitionData.asset"},"motions":{"ando01":[{"file":"ando01.mtn"}],"angry01":[{"file":"angry01.mtn"}],"angry02":[{"file":"angry02.mtn"}],"angry03":[{"file":"angry03.mtn"}],"angry04":[{"file":"angry04.mtn"}],"bye01":[{"file":"bye01.mtn"}],"bye02":[{"file":"bye02.mtn"}],"cry01":[{"file":"cry01.mtn"}],"cry02":[{"file":"cry02.mtn"}],"gacha01":[{"file":"gacha01.mtn"}],"idle01":[{"file":"idle01.mtn"}],"kandou01":[{"file":"kandou01.mtn"}],"kime01":[{"file":"kime01.mtn"}],"nf01":[{"file":"nf01.mtn"}],"nf02":[{"file":"nf02.mtn"}],"nf02_ingameV2":[{"file":"nf02_ingameV2.mtn"}],"nf03":[{"file":"nf03.mtn"}],"nf04":[{"file":"nf04.mtn"}],"nf05":[{"file":"nf05.mtn"}],"nf_left01":[{"file":"nf_left01.mtn"}],"nf_right01":[{"file":"nf_right01.mtn"}],"nnf01":[{"file":"nnf01.mtn"}],"nnf02":[{"file":"nnf02.mtn"}],"nnf03":[{"file":"nnf03.mtn"}],"nnf04":[{"file":"nnf04.mtn"}],"nnf05":[{"file":"nnf05.mtn"}],"nnf_left01":[{"file":"nnf_left01.mtn"}],"nnf_right01":[{"file":"nnf_right01.mtn"}],"pui01":[{"file":"pui01.mtn"}],"sad01":[{"file":"sad01.mtn"}],"sad02":[{"file":"sad02.mtn"}],"sad03":[{"file":"sad03.mtn"}],"serious01":[{"file":"serious01.mtn"}],"serious02":[{"file":"serious02.mtn"}],"shame01":[{"file":"shame01.mtn"}],"shame02":[{"file":"shame02.mtn"}],"sigh01":[{"file":"sigh01.mtn"}],"sigh02":[{"file":"sigh02.mtn"}],"smile01":[{"file":"smile01.mtn"}],"smile02":[{"file":"smile02.mtn"}],"smile03":[{"file":"smile03.mtn"}],"smile04":[{"file":"smile04.mtn"}],"surprised01":[{"file":"surprised01.mtn"}],"surprised02":[{"file":"surprised02.mtn"}],"thinking01":[{"file":"thinking01.mtn"}]},"expressions":[{"name":"ando01","file":"../040_general/ando01.exp.json"},{"name":"angry01","file":"../040_general/angry01.exp.json"},{"name":"angry02","file":"../040_general/angry02.exp.json"},{"name":"angry03","file":"../040_general/angry03.exp.json"},{"name":"angry04","file":"../040_general/angry04.exp.json"},{"name":"bye01","file":"../040_general/bye01.exp.json"},{"name":"bye02","file":"../040_general/bye02.exp.json"},{"name":"cry01","file":"../040_general/cry01.exp.json"},{"name":"cry02","file":"../040_general/cry02.exp.json"},{"name":"default","file":"../040_general/default.exp.json"},{"name":"idle01","file":"../040_general/idle01.exp.json"},{"name":"kandou01","file":"../040_general/kandou01.exp.json"},{"name":"kime01","file":"../040_general/kime01.exp.json"},{"name":"pui01","file":"../040_general/pui01.exp.json"},{"name":"sad01","file":"../040_general/sad01.exp.json"},{"name":"sad02","file":"../040_general/sad02.exp.json"},{"name":"sad03","file":"../040_general/sad03.exp.json"},{"name":"serious01","file":"../040_general/serious01.exp.json"},{"name":"serious02","file":"../040_general/serious02.exp.json"},{"name":"shame01","file":"../040_general/shame01.exp.json"},{"name":"shame02","file":"../040_general/shame02.exp.json"},{"name":"sigh01","file":"../040_general/sigh01.exp.json"},{"name":"sigh02","file":"../040_general/sigh02.exp.json"},{"name":"smile01","file":"../040_general/smile01.exp.json"},{"name":"smile02","file":"../040_general/smile02.exp.json"},{"name":"smile03","file":"../040_general/smile03.exp.json"},{"name":"smile04","file":"../040_general/smile04.exp.json"},{"name":"surprised01","file":"../040_general/surprised01.exp.json"},{"name":"surprised02","file":"../040_general/surprised02.exp.json"},{"name":"thinking01","file":"../040_general/thinking01.exp.json"}]}